frequency_controller/__init__.py
frequency_controller/async_tools.py
frequency_controller/sync_tools.py
frequency_controller-0.0.6.dist-info/LICENSE
frequency_controller-0.0.6.dist-info/METADATA
frequency_controller-0.0.6.dist-info/WHEEL
frequency_controller-0.0.6.dist-info/top_level.txt
frequency_controller-0.0.6.dist-info/RECORD
