Metadata-Version: 2.1
Name: frequency-controller
Version: 0.0.6
Summary: Setting a limitation for usage frequency. Read more: https://github.com/ClericPy/frequency_controller.
Home-page: https://github.com/ClericPy/frequency_controller
Author: ClericPy
Author-email: clericpy@gmail.com
License: MIT License
Keywords: frequency limitation async multi-thread asyncio asynchronous
Platform: any
Classifier: License :: OSI Approved :: MIT License
Classifier: Programming Language :: Python
Classifier: Programming Language :: Python :: 2
Classifier: Programming Language :: Python :: 3
Classifier: Programming Language :: Python :: 2.7
Classifier: Programming Language :: Python :: 3.6
Classifier: Programming Language :: Python :: 3.7
Classifier: Programming Language :: Python :: 3.8
Requires-Python: >=2.7
Requires-Dist: futures
